radius/__init__.py
radius/classes/plugin_base.py
radius/classes/tool_base.py
radius/classes/wallet_client_base.py
radius/decorators/tool.py
radius/types/chain.py
radius/utils/get_tools.py
radius/utils/snake_case.py
radius_ai_agent_sdk-1.0.0.dist-info/METADATA
radius_ai_agent_sdk-1.0.0.dist-info/WHEEL
radius_ai_agent_sdk-1.0.0.dist-info/top_level.txt
radius_ai_agent_sdk-1.0.0.dist-info/RECORD
