Metadata-Version: 2.2
Name: radius-ai-agent-sdk
Version: 1.0.0
Summary: Radius AI Agent SDK is an open-source framework for connecting AI agents to the Radius network
Author-email: Matt Dionis <matt.dionis@radiustechnologysystems.com>
License: MIT
Project-URL: Homepage, https://github.com/radiustechsystems/ai-agent-toolkit
Project-URL: Documentation, https://github.com/radiustechsystems/ai-agent-toolkit/blob/main/python/src/radius_ai_agent_sdk/README.md
Project-URL: Repository, https://github.com/radiustechsystems/ai-agent-toolkit/blob/main/python/src/radius_ai_agent_sdk
Project-URL: Issues, https://github.com/radiustechsystems/ai-agent-toolkit/issues
Project-URL: Changelog, https://github.com/radiustechsystems/ai-agent-toolkit/blob/main/python/CHANGELOG.md
Keywords: radius,sdk,web3,agents,ai
Classifier: Development Status :: 3 - Alpha
Classifier: Intended Audience :: Developers
Classifier: License :: OSI Approved :: MIT License
Classifier: Programming Language :: Python :: 3
Classifier: Programming Language :: Python :: 3.10
Classifier: Programming Language :: Python :: 3.11
Classifier: Programming Language :: Python :: 3.12
Requires-Python: >=3.10
Requires-Dist: pydantic>=2.0.0
Requires-Dist: asyncio>=3.4.1
Requires-Dist: typing-extensions>=4.12.2
